mitmproxy2swagger/__init__.py
mitmproxy2swagger/console_util.py
mitmproxy2swagger/har_capture_reader.py
mitmproxy2swagger/mitmproxy2swagger.py
mitmproxy2swagger/mitmproxy_capture_reader.py
mitmproxy2swagger/swagger_util.py
mitmproxy2swagger/test_mitmproxy2swagger.py
mitmproxy2swagger/test_openapi_compliance.py
mitmproxy2swagger/testing_util.py
mitmproxy2swagger-0.14.0.dist-info/METADATA
mitmproxy2swagger-0.14.0.dist-info/WHEEL
mitmproxy2swagger-0.14.0.dist-info/entry_points.txt
mitmproxy2swagger-0.14.0.dist-info/RECORD
