Metadata-Version: 2.1
Name: mitmproxy2swagger
Version: 0.14.0
Summary: 
License: MIT
Author: alufers
Author-email: alufers@wp.pl
Requires-Python: >=3.10,<4.0
Classifier: License :: OSI Approved :: MIT License
Classifier: Programming Language :: Python :: 3
Classifier: Programming Language :: Python :: 3.10
Classifier: Programming Language :: Python :: 3.11
Classifier: Programming Language :: Python :: 3.12
Requires-Dist: json-stream (>=2.3.2,<3.0.0)
Requires-Dist: mitmproxy (>=11.0.2,<12.0.0)
Requires-Dist: msgpack (>=1.0.7,<2.0.0)
Requires-Dist: ruamel.yaml (>=0.17.32,<0.19.0)
